setup.py
ebeth_helpers/__init__.py
ebeth_helpers.egg-info/PKG-INFO
ebeth_helpers.egg-info/SOURCES.txt
ebeth_helpers.egg-info/dependency_links.txt
ebeth_helpers.egg-info/not-zip-safe
ebeth_helpers.egg-info/requires.txt
ebeth_helpers.egg-info/top_level.txt