Metadata-Version: 1.0
Name: ebeth-helpers
Version: 0.5
Summary: mini tools to speed up gbdx work
Home-page: https://github.com/lizasapphire/gbdx_helpers
Author: Elizabeth Golden
Author-email: elizabeth.golden@digitalglobe.com
License: UNKNOWN
Platform: UNKNOWN
